{
	"id": "f6fa99bb-fbba-4674-8495-e94be588ad85",
	"name": "FFM_STAGGING_ENVIRONMENT",
	"values": [
		{
			"key": "url_auth",
			"value": "167.99.73.130:30287",
			"enabled": true
		},
		{
			"key": "url_user_management",
			"value": "167.99.73.130:30288",
			"enabled": true
		},
		{
			"key": "url_task_service",
			"value": "167.99.73.130:30286",
			"enabled": true
		},
		{
			"key": "url_field_attendance",
			"value": "167.99.73.130:30289",
			"enabled": true
		},
		{
			"key": "url_field_delivery",
			"value": "167.99.73.130:30285",
			"enabled": true
		},
		{
			"key": "company_id",
			"value": "900",
			"enabled": true
		},
		{
			"key": "auth_token_company_admin",
			"value": "",
			"enabled": true
		},
		{
			"key": "auth_token_techser4u_admin",
			"value": "",
			"enabled": true
		},
		{
			"key": "auth_token_company's_another_admin",
			"value": "",
			"enabled": true
		},
		{
			"key": "user_id_company_admin",
			"value": "",
			"enabled": true
		},
		{
			"key": "user_id_techserve4u_admin",
			"value": "",
			"enabled": true
		},
		{
			"key": "user_id_company's_another_admin",
			"value": "",
			"enabled": true
		},
		{
			"key": "auth_token_app_user",
			"value": "",
			"enabled": true
		},
		{
			"key": "user_id_app_user",
			"value": "",
			"enabled": true
		}
	],
	"_postman_variable_scope": "environment",
	"_postman_exported_at": "2020-11-29T02:35:21.577Z",
	"_postman_exported_using": "Postman/7.35.0"
}